Workbook

Sheet Raw Data
A1: Particulars (amount in crs) | B1: FY(2025-26) | C1: FY(2024-25) | D1: FY(2023-24) | E1: FY(2022-23)
A2: Revenue from Operations | B2: 64468 | C2: 61328 | D2: 61896 | E2: 60580
A3: Expenses | B3: 51157 | C3: 48256 | D3: 13926 | E3: 13344
A4: Profit After Tax | B4: 15059 | C4: 10671 | D4: 10282 | E4: 10143
A5: Total Assets | B5: 79752 | C5: 79880 | D5: 78499 | E5: 73087
A6: Total Equity | B6: 49008 | C6: 49609 | D6: 51423 | E6: 50522
A7: Total Borrowings | B7: 1104 | C7: 1243 | D7: 1106 | E7: 807
A8: Currenty Assets | B8: 19021 | C8: 22051 | D8: 21324 | E8: 16998
A9: Current Liabilities | B9: 15549 | C9: 16537 | D9: 12876 | E9: 12028
A10: Operating Cashflow | B10: 10999 | C10: 11886 | D10: 15469 | E10: 9991

Sheet Calculations
A1: Particulars | B1: FY(2025-26) | C1: FY(2024-25) | D1: FY(2023-24) | E1: FY(2022-23)
A2: Revenue Growth | B2: =('Raw Data'!B2-'Raw Data'!C2)/'Raw Data'!C2*100 -> 5.1200104 | C2: =('Raw Data'!C2-'Raw Data'!D2)/'Raw Data'!D2*100 -> -0.91766835 | D2: =('Raw Data'!D2-'Raw Data'!E2)/'Raw Data'!E2*100 -> 2.1723341 | E2: N/A
A3: Net Profit Margin | B3: ='Raw Data'!B4/'Raw Data'!B2*100 -> 23.358876 | C3: ='Raw Data'!C4/'Raw Data'!C2*100 -> 17.399883 | D3: ='Raw Data'!D4/'Raw Data'!D2*100 -> 16.611736 | E3: ='Raw Data'!E4/'Raw Data'!E2*100 -> 16.74315
A4: Return On Equity | B4: ='Raw Data'!B4/'Raw Data'!B6*100 -> 30.727636 | C4: ='Raw Data'!C4/'Raw Data'!C6*100 -> 21.51021 | D4: ='Raw Data'!D4/'Raw Data'!D6*100 -> 19.994944 | E4: ='Raw Data'!E4/'Raw Data'!E6*100 -> 20.076402
A5: Debt to Equity Ratio | B5: ='Raw Data'!B7/'Raw Data'!B6 -> 0.022526934 | C5: ='Raw Data'!C7/'Raw Data'!C6 -> 0.025055937 | D5: ='Raw Data'!D7/'Raw Data'!D6 -> 0.021507886 | E5: ='Raw Data'!E7/'Raw Data'!E6 -> 0.015973239
A6: Current Ratio | B6: ='Raw Data'!B8/'Raw Data'!B9 -> 1.2232941 | C6: ='Raw Data'!C8/'Raw Data'!C9 -> 1.3334341 | D6: ='Raw Data'!D8/'Raw Data'!D9 -> 1.6561044 | E6: ='Raw Data'!E8/'Raw Data'!E9 -> 1.4132025
A7: Operating Cashflow | B7: ='Raw Data'!B10/'Raw Data'!B4 -> 0.73039378 | C7: ='Raw Data'!C10/'Raw Data'!C4 -> 1.11386 | D7: ='Raw Data'!D10/'Raw Data'!D4 -> 1.5044738 | E7: ='Raw Data'!E10/'Raw Data'!E4 -> 0.9850143

Sheet Dashboard

Sheet Insights
A1: Financial Area | B1: Observation | C1: Interpretation | D1: Recommendation
A2: Revenue Growth | B2: Revenue grew by 5.12% in FY 2025–26. | C2: Revenue growth recovered after a slight decline. | D2: Monitor sales and pricing trends.
A3: Profitability | B3: Net profit margin increased to 23.36%. | C3: Reported profitability improved. | D3: Verify the impact of expenses and exceptional items.
A4: Liquidity | B4: Current ratio declined from 1.33 to 1.22. | C4: Short-term asset coverage decreased. | D4: Monitor working capital and current liabilities.
A5: Capital Structure | B5: Debt-to-equity ratio stood at 0.02. | C5: Borrowings are low relative to equity. | D5: Monitor borrowings and other financial commitments.
A6: Cash Flow | B6: Operating cash flow fell to ₹10,999 crore. | C6: Cash generation weakened despite revenue growth. | D6: Investigate working capital and operating cash flows.
